odoo/addons/mrp_stock_move_line_qty_picked/README.rst
odoo/addons/mrp_stock_move_line_qty_picked/__init__.py
odoo/addons/mrp_stock_move_line_qty_picked/__manifest__.py
odoo/addons/mrp_stock_move_line_qty_picked/i18n/it.po
odoo/addons/mrp_stock_move_line_qty_picked/i18n/mrp_stock_move_line_qty_picked.pot
odoo/addons/mrp_stock_move_line_qty_picked/readme/CONTRIBUTORS.md
odoo/addons/mrp_stock_move_line_qty_picked/readme/DESCRIPTION.md
odoo/addons/mrp_stock_move_line_qty_picked/static/description/icon.png
odoo/addons/mrp_stock_move_line_qty_picked/static/description/index.html
odoo/addons/mrp_stock_move_line_qty_picked/views/mrp_production.xml
odoo_addon_mrp_stock_move_line_qty_picked-18.0.1.0.0.4.dist-info/METADATA
odoo_addon_mrp_stock_move_line_qty_picked-18.0.1.0.0.4.dist-info/WHEEL
odoo_addon_mrp_stock_move_line_qty_picked-18.0.1.0.0.4.dist-info/top_level.txt
odoo_addon_mrp_stock_move_line_qty_picked-18.0.1.0.0.4.dist-info/RECORD
