Metadata-Version: 2.1
Name: odoo-addon-mrp_stock_move_line_qty_picked
Version: 18.0.1.0.0.4
Requires-Python: >=3.10
Requires-Dist: odoo-addon-stock_move_line_qty_picked==18.0.*
Requires-Dist: odoo==18.0.*
Summary: Adapt functionality of stock_move_line_qty_picked into MRP
Home-page: https://github.com/OCA/manufacture
License: AGPL-3
Author: ForgeFlow, Odoo Community Association (OCA)
Author-email: support@odoo-community.org
Classifier: Programming Language :: Python
Classifier: Framework :: Odoo
Classifier: Framework :: Odoo :: 18.0
Classifier: License :: OSI Approved :: GNU Affero General Public License v3
